{
  "id": "agm80l",
  "name": "AGM80L",
  "brand": "로케트",
  "brandKey": "rocket",
  "type": "AGM",
  "capacity": "80Ah",
  "cca": "800CCA",
  "images": {
    "main": "/assets/batteries/AGM80L/01-main.png",
    "productBox": "/assets/batteries/AGM80L/02-product-box.png",
    "boxFront": "/assets/batteries/AGM80L/03-box-front.png",
    "boxAngle": "/assets/batteries/AGM80L/04-box-angle.png",
    "productBoxAngle": "/assets/batteries/AGM80L/05-product-box-angle.png",
    "labelTop": "/assets/batteries/AGM80L/06-label-top.png",
    "frontLabel": "/assets/batteries/AGM80L/07-front-label.png"
  },
  "mapping": [
    {
      "original": "AGM80.png",
      "renamed": "01-main.png",
      "path": "/assets/batteries/AGM80L/01-main.png",
      "usage": "대표 썸네일 / 상품카드 / 검색결과"
    },
    {
      "original": "BTP08000.png",
      "renamed": "02-product-box.png",
      "path": "/assets/batteries/AGM80L/02-product-box.png",
      "usage": "제품+박스 정면 / 상세 상단"
    },
    {
      "original": "BTP07876.png",
      "renamed": "03-box-front.png",
      "path": "/assets/batteries/AGM80L/03-box-front.png",
      "usage": "박스 정면 / 패키지 안내"
    },
    {
      "original": "BTP07879.png",
      "renamed": "04-box-angle.png",
      "path": "/assets/batteries/AGM80L/04-box-angle.png",
      "usage": "박스 사선 / 포장 상태"
    },
    {
      "original": "BTP07883.png",
      "renamed": "05-product-box-angle.png",
      "path": "/assets/batteries/AGM80L/05-product-box-angle.png",
      "usage": "제품+박스 사선 / 브랜드/상세 비주얼"
    },
    {
      "original": "BTP07885.png",
      "renamed": "06-label-top.png",
      "path": "/assets/batteries/AGM80L/06-label-top.png",
      "usage": "상단 라벨 / 12V·800CCA·80Ah·단자 설명"
    },
    {
      "original": "BTP07888.png",
      "renamed": "07-front-label.png",
      "path": "/assets/batteries/AGM80L/07-front-label.png",
      "usage": "정면 라벨 / 제품명·규격 확인"
    }
  ]
}